odoo8_addon_stock_picking_partner_lang-8.0.1.0.0-py2.7-nspkg.pth
odoo_addons/stock_picking_partner_lang/__openerp__.py
odoo_addons/stock_picking_partner_lang/picking_report.xml
odoo_addons/stock_picking_partner_lang/__init__.py
odoo_addons/stock_picking_partner_lang/README.rst
odoo_addons/stock_picking_partner_lang/views/stock_picking_partner_language.xml
odoo8_addon_stock_picking_partner_lang-8.0.1.0.0.dist-info/top_level.txt
odoo8_addon_stock_picking_partner_lang-8.0.1.0.0.dist-info/WHEEL
odoo8_addon_stock_picking_partner_lang-8.0.1.0.0.dist-info/RECORD
odoo8_addon_stock_picking_partner_lang-8.0.1.0.0.dist-info/metadata.json
odoo8_addon_stock_picking_partner_lang-8.0.1.0.0.dist-info/DESCRIPTION.rst
odoo8_addon_stock_picking_partner_lang-8.0.1.0.0.dist-info/METADATA
odoo8_addon_stock_picking_partner_lang-8.0.1.0.0.dist-info/namespace_packages.txt
