Metadata-Version: 2.0
Name: odoo8-addon-stock-picking-partner-lang
Version: 8.0.1.0.0
Summary: Adds report for stock picking in partner language
Home-page: http://www.agilebg.com
Author: UNKNOWN
Author-email: UNKNOWN
License: UNKNOWN
Platform: UNKNOWN
Requires-Dist: odoo (<9.0a,>=8.0a)
Classifier: Programming Language :: Python :: 2.7
Classifier: Framework :: Odoo
